[
  {
    "id": 1,
    "customerId": 2,
    "paymentMethod": {
      "_type": "BOLETO",
      "barcode": "07164183651096198212372167975532757146386174",
      "dueDate": "2026-07-01"
    },
    "address": {
      "cep": "59063-150",
      "state": "RN",
      "city": "Natal",
      "neighbor": "Lagoa Nova",
      "street": "São José",
      "number": "1240",
      "complement": ""
    },
    "items": [
      {
        "product": {
          "id": 1,
          "name": "Notebook Gamer",
          "description": "Notebook com placa de vídeo dedicada",
          "stockQuantity": 8,
          "price": 5999.90,
          "category": {
            "id": 2,
            "name": "Computadores",
            "description": "Desktops e notebooks",
            "parentCategory": {
              "id": 1,
              "name": "Eletrônicos",
              "description": "Produtos eletrônicos em geral"
            }
          },
          "weight": 2.35,
          "technicalSpecs": "Intel Core i7, 16GB RAM, SSD 1TB, RTX 4060",
          "warrantyMonths": 24,
          "totalRating": 4.8,
          "reviews": []
        },
        "quantity": 1,
        "subtotal": 5999.90
      }
    ],
    "totalValue": 5419.91,
    "situation": "SENT",
    "shipping": {
      "transporter": {
        "id": 1,
        "name": "Correios",
        "shippingFactor": 1.00,
        "deliveryDaysAdjustment": 0,
        "contact": "0800-725-0100",
        "website": "https://www.correios.com.br"
      },
      "address": {
        "cep": "59063-150",
        "state": "RN",
        "city": "Natal",
        "neighbor": "Lagoa Nova",
        "street": "São José",
        "number": "1240",
        "complement": ""
      },
      "totalWeight": 2.349999904632568359375,
      "shippingValue": 20.00,
      "averageDeliveryTime": 10
    },
    "dateTimePurchase": "2026-06-28T15:57:39.677945"
  },
  {
    "id": 2,
    "customerId": 2,
    "paymentMethod": {
      "_type": "BOLETO",
      "barcode": "51202172785775114791723491383636717689943567",
      "dueDate": "2026-07-01"
    },
    "address": {
      "cep": "59063-150",
      "state": "RN",
      "city": "Natal",
      "neighbor": "Lagoa Nova",
      "street": "São José",
      "number": "1240",
      "complement": ""
    },
    "items": [
      {
        "product": {
          "id": 2,
          "name": "Mouse Sem Fio",
          "description": "Mouse óptico ergonômico",
          "stockQuantity": 47,
          "price": 129.90,
          "category": {
            "id": 3,
            "name": "Periféricos",
            "description": "Mouse, teclado e acessórios",
            "parentCategory": {
              "id": 1,
              "name": "Eletrônicos",
              "description": "Produtos eletrônicos em geral"
            }
          },
          "weight": 0.12,
          "technicalSpecs": "Conexão 2.4GHz, DPI ajustável",
          "warrantyMonths": 12,
          "totalRating": 4.5,
          "reviews": []
        },
        "quantity": 2,
        "subtotal": 259.80
      }
    ],
    "totalValue": 252.82,
    "situation": "RECEIVED_BY_TRANSPORTER",
    "shipping": {
      "transporter": {
        "id": 2,
        "name": "Loggi",
        "shippingFactor": 0.95,
        "deliveryDaysAdjustment": -1,
        "contact": "contato@loggi.com",
        "website": "https://www.loggi.com"
      },
      "address": {
        "cep": "59063-150",
        "state": "RN",
        "city": "Natal",
        "neighbor": "Lagoa Nova",
        "street": "São José",
        "number": "1240",
        "complement": ""
      },
      "totalWeight": 0.23999999463558197021484375,
      "shippingValue": 19.00,
      "averageDeliveryTime": 9
    },
    "dateTimePurchase": "2026-06-28T16:04:05.091273"
  },
  {
    "id": 3,
    "customerId": 2,
    "paymentMethod": {
      "_type": "PIX",
      "pixKey": "08611101976994719782PIXCODE0032172155"
    },
    "address": {
      "cep": "59063-150",
      "state": "RN",
      "city": "Natal",
      "neighbor": "Lagoa Nova",
      "street": "São José",
      "number": "1240",
      "complement": ""
    },
    "items": [
      {
        "product": {
          "id": 2,
          "name": "Mouse Sem Fio",
          "description": "Mouse óptico ergonômico",
          "stockQuantity": 46,
          "price": 129.90,
          "category": {
            "id": 3,
            "name": "Periféricos",
            "description": "Mouse, teclado e acessórios",
            "parentCategory": {
              "id": 1,
              "name": "Eletrônicos",
              "description": "Produtos eletrônicos em geral"
            }
          },
          "weight": 0.12,
          "technicalSpecs": "Conexão 2.4GHz, DPI ajustável",
          "warrantyMonths": 12,
          "totalRating": 4.5,
          "reviews": []
        },
        "quantity": 1,
        "subtotal": 129.90
      }
    ],
    "totalValue": 132.41,
    "situation": "DELIVERED",
    "shipping": {
      "transporter": {
        "id": 3,
        "name": "Jadlog",
        "shippingFactor": 1.10,
        "deliveryDaysAdjustment": 1,
        "contact": "0800-704-1103",
        "website": "https://www.jadlog.com.br"
      },
      "address": {
        "cep": "59063-150",
        "state": "RN",
        "city": "Natal",
        "neighbor": "Lagoa Nova",
        "street": "São José",
        "number": "1240",
        "complement": ""
      },
      "totalWeight": 0.119999997317790985107421875,
      "shippingValue": 22.00,
      "averageDeliveryTime": 11
    },
    "dateTimePurchase": "2026-06-28T16:33:50.460235"
  }
]